odoo/addons/l10n_it_vat_settlement_date/README.rst
odoo/addons/l10n_it_vat_settlement_date/__init__.py
odoo/addons/l10n_it_vat_settlement_date/__manifest__.py
odoo/addons/l10n_it_vat_settlement_date/i18n/it.po
odoo/addons/l10n_it_vat_settlement_date/i18n/l10n_it_vat_settlement_date.pot
odoo/addons/l10n_it_vat_settlement_date/models/__init__.py
odoo/addons/l10n_it_vat_settlement_date/models/account_move.py
odoo/addons/l10n_it_vat_settlement_date/models/account_move_line.py
odoo/addons/l10n_it_vat_settlement_date/models/account_tax.py
odoo/addons/l10n_it_vat_settlement_date/models/account_vat_period_end_statement.py
odoo/addons/l10n_it_vat_settlement_date/models/comunicazione_liquidazione.py
odoo/addons/l10n_it_vat_settlement_date/readme/CONTRIBUTORS.md
odoo/addons/l10n_it_vat_settlement_date/readme/DESCRIPTION.md
odoo/addons/l10n_it_vat_settlement_date/reports/__init__.py
odoo/addons/l10n_it_vat_settlement_date/reports/report_registro_iva.xml
odoo/addons/l10n_it_vat_settlement_date/reports/vat_statement.py
odoo/addons/l10n_it_vat_settlement_date/static/description/icon.png
odoo/addons/l10n_it_vat_settlement_date/static/description/index.html
odoo/addons/l10n_it_vat_settlement_date/tests/__init__.py
odoo/addons/l10n_it_vat_settlement_date/tests/test_open_tax_balances.py
odoo/addons/l10n_it_vat_settlement_date/tests/test_vat_period_end_statement.py
odoo/addons/l10n_it_vat_settlement_date/tests/test_vat_registry.py
odoo/addons/l10n_it_vat_settlement_date/views/account_move_views.xml
odoo/addons/l10n_it_vat_settlement_date/wizard/__init__.py
odoo/addons/l10n_it_vat_settlement_date/wizard/open_tax_balances.py
odoo/addons/l10n_it_vat_settlement_date/wizard/report_registro_iva_xlsx.py
odoo_addon_l10n_it_vat_settlement_date-18.0.1.0.1.2.dist-info/METADATA
odoo_addon_l10n_it_vat_settlement_date-18.0.1.0.1.2.dist-info/WHEEL
odoo_addon_l10n_it_vat_settlement_date-18.0.1.0.1.2.dist-info/top_level.txt
odoo_addon_l10n_it_vat_settlement_date-18.0.1.0.1.2.dist-info/RECORD
