Metadata-Version: 2.1
Name: odoo-addon-l10n_it_vat_settlement_date
Version: 18.0.1.0.1.2
Requires-Python: >=3.10
Requires-Dist: odoo-addon-account_tax_balance==18.0.*
Requires-Dist: odoo-addon-l10n_it_account_vat_period_end_settlement==18.0.*
Requires-Dist: odoo-addon-l10n_it_vat_registries==18.0.*
Requires-Dist: odoo-addon-l10n_it_vat_settlement_communication==18.0.*
Requires-Dist: odoo==18.0.*
Summary: Settlement date for VAT Statement
Home-page: https://github.com/OCA/l10n-italy/tree/18.0/l10n_it_vat_settlement_date
License: AGPL-3
Author: Marco Colombo, Odoo Community Association (OCA)
Author-email: support@odoo-community.org
Classifier: Programming Language :: Python
Classifier: Framework :: Odoo
Classifier: Framework :: Odoo :: 18.0
Classifier: License :: OSI Approved :: GNU Affero General Public License v3
